{
	"clientId": "",
	"guildId": "",
	"token": "",
	"ALCHEMY_RINKEBY_URL": "",
	"INFURA_RINKEBY_URL": "",
	"MOVE_URL": "",
	"PRIVATE_KEY": "",
	"FROM_ADDRESS": "",
	"CONTRACT_ADDRESSES": {
		"arb": "",
		"move": ""
	},
	"DISTRIBUTOR_ADDRESSES": {
		"arb": "",
		"move": ""
	},
	"AMOUNT_ETH": {
		"arb": "0.01",
		"move": "0.1",
		"bera": "0.2"
	},
	"CHAIN_COOLDOWN": {
		"arb": 15000,
		"move": 30000
	},
	"amount": "0.1",
	"maxFeePerGas": 95000000000,
	"activityType": "",
	"activityName": "",
	"arbiscanUrl": "https://sepolia.arbiscan.io/tx/",
	"movementExplorerUrl": "https://explorer.devnet.imola.movementlabs.xyz/#/txn/",
	"infura": true,
	"approvedRoles": [
		"869338295207870485",
		"869605103701737482",
		"869605623208214573",
		"902645751631454258"
	]
}